mower/controller/cli_controller.py
mower/exception/bad_config_exception.py
mower/exception/collision_exception.py
mower/model/action.py
mower/model/lawn.py
mower/model/mower.py
mower/model/orientation.py
mower/model/position.py
mower/model/turn_type.py
mower/service/file_lawn_builder_service.py
mower/service/lawn_builder_service.py
mower/service/mowing_service.py
mower_cli-0.1.1.dist-info/METADATA
mower_cli-0.1.1.dist-info/WHEEL
mower_cli-0.1.1.dist-info/entry_points.txt
mower_cli-0.1.1.dist-info/RECORD
