Metadata-Version: 2.1
Name: mower-cli
Version: 0.1.1
Summary: 
Author: Benoit Puertolas
Requires-Python: >=3.8,<4.0
Classifier: Programming Language :: Python :: 3
Classifier: Programming Language :: Python :: 3.8
Classifier: Programming Language :: Python :: 3.9
Classifier: Programming Language :: Python :: 3.10
Classifier: Programming Language :: Python :: 3.11
Requires-Dist: pydantic (>=2.4.2,<3.0.0)
